simar_co6_101703543/__init__.py
simar_co6_101703543/topsis.py
simar_co6_101703543-0.0.1.dist-info/LICENSE
simar_co6_101703543-0.0.1.dist-info/METADATA
simar_co6_101703543-0.0.1.dist-info/WHEEL
simar_co6_101703543-0.0.1.dist-info/top_level.txt
simar_co6_101703543-0.0.1.dist-info/RECORD
