Metadata-Version: 2.1
Name: simar-co6-101703543
Version: 0.0.1
Summary: A small package that showcases topsis approach
Home-page: https://github.com/simargulati/simar_coe6_101703543
Author: Simarpreet Singh
Author-email: sgulati_be17@thapar.edu
License: UNKNOWN
Platform: UNKNOWN
Classifier: Programming Language :: Python :: 3
Classifier: License :: OSI Approved :: MIT License
Classifier: Operating System :: OS Independent
Requires-Python: >=3.6
